<?xml version="1.0" encoding="UTF-8"?>
<results title="frequencies">
 <result title="frequency" word="health" count="114"/>
 <result title="frequency" word="MENA" count="68"/>
 <result title="frequency" word="countries" count="48"/>
 <result title="frequency" word="region" count="44"/>
 <result title="frequency" word="systems" count="37"/>
 <result title="frequency" word="Health" count="36"/>
 <result title="frequency" word="World" count="27"/>
 <result title="frequency" word="services" count="26"/>
 <result title="frequency" word="East" count="21"/>
 <result title="frequency" word="care" count="21"/>
 <result title="frequency" word="population" count="21"/>
 <result title="frequency" word="Middle" count="20"/>
 <result title="frequency" word="significant" count="20"/>
 <result title="frequency" word="{border-style" count="20"/>
 <result title="frequency" word="px;}" count="18"/>
 <result title="frequency" word="#ffffff;}" count="17"/>
 <result title="frequency" word="Arab" count="17"/>
 <result title="frequency" word="North" count="17"/>
 <result title="frequency" word="Development" count="15"/>
 <result title="frequency" word="challenges" count="15"/>
 <result title="frequency" word="public" count="14"/>
 <result title="frequency" word="address" count="13"/>
 <result title="frequency" word="data" count="13"/>
 <result title="frequency" word="private" count="13"/>
 <result title="frequency" word="including" count="12"/>
 <result title="frequency" word="medical" count="12"/>
 <result title="frequency" word="national" count="12"/>
 <result title="frequency" word="number" count="12"/>
 <result title="frequency" word="region." count="12"/>
 <result title="frequency" word="mortality" count="11"/>
 <result title="frequency" word="need" count="11"/>
 <result title="frequency" word="prevalence" count="11"/>
 <result title="frequency" word="Population" count="10"/>
 <result title="frequency" word="United" count="10"/>
 <result title="frequency" word="available" count="10"/>
 <result title="frequency" word="regional" count="10"/>
 <result title="frequency" word="require" count="10"/>
 <result title="frequency" word="Africa" count="9"/>
 <result title="frequency" word="Bank" count="9"/>
 <result title="frequency" word="BankWashington," count="9"/>
 <result title="frequency" word="Saudi" count="9"/>
 <result title="frequency" word="September" count="9"/>
 <result title="frequency" word="Systems" count="9"/>
 <result title="frequency" word="development" count="9"/>
 <result title="frequency" word="increasing" count="9"/>
 <result title="frequency" word="resource" count="9"/>
 <result title="frequency" word="services." count="9"/>
 <result title="frequency" word="workers" count="9"/>
 <result title="frequency" word="Global" count="8"/>
 <result title="frequency" word="Public" count="8"/>
 <result title="frequency" word="countries," count="8"/>
 <result title="frequency" word="curative" count="8"/>
 <result title="frequency" word="delivery" count="8"/>
 <result title="frequency" word="expenditures" count="8"/>
 <result title="frequency" word="face" count="8"/>
 <result title="frequency" word="global" count="8"/>
 <result title="frequency" word="governments" count="8"/>
 <result title="frequency" word="growth" count="8"/>
 <result title="frequency" word="high" count="8"/>
 <result title="frequency" word="px;" count="8"/>
 <result title="frequency" word="quality" count="8"/>
 <result title="frequency" word="rate" count="8"/>
 <result title="frequency" word="rates" count="8"/>
 <result title="frequency" word="sector" count="8"/>
 <result title="frequency" word="service" count="8"/>
 <result title="frequency" word="years" count="8"/>
 <result title="frequency" word="{font-family" count="8"/>
 <result title="frequency" word="August" count="7"/>
 <result title="frequency" word="Burden" count="7"/>
 <result title="frequency" word="Disease" count="7"/>
 <result title="frequency" word="Figure" count="7"/>
 <result title="frequency" word="Reference" count="7"/>
 <result title="frequency" word="Yemen" count="7"/>
 <result title="frequency" word="achievements" count="7"/>
 <result title="frequency" word="areas" count="7"/>
 <result title="frequency" word="article" count="7"/>
 <result title="frequency" word="average" count="7"/>
 <result title="frequency" word="changes" count="7"/>
 <result title="frequency" word="coverage" count="7"/>
 <result title="frequency" word="disease" count="7"/>
 <result title="frequency" word="diseases" count="7"/>
 <result title="frequency" word="font-size" count="7"/>
 <result title="frequency" word="human" count="7"/>
 <result title="frequency" word="largely" count="7"/>
 <result title="frequency" word="live" count="7"/>
 <result title="frequency" word="management" count="7"/>
 <result title="frequency" word="particularly" count="7"/>
 <result title="frequency" word="region," count="7"/>
 <result title="frequency" word="services," count="7"/>
 <result title="frequency" word="traditional" count="7"/>
 <result title="frequency" word="(%)" count="6"/>
 <result title="frequency" word="(accessed" count="6"/>
 <result title="frequency" word="Challenges" count="6"/>
 <result title="frequency" word="Egypt" count="6"/>
 <result title="frequency" word="Elsevier" count="6"/>
 <result title="frequency" word="Human" count="6"/>
 <result title="frequency" word="Regional" count="6"/>
 <result title="frequency" word="WHO/EMRO" count="6"/>
 <result title="frequency" word="acute" count="6"/>
 <result title="frequency" word="birth" count="6"/>
 <result title="frequency" word="burden" count="6"/>
 <result title="frequency" word="continue" count="6"/>
 <result title="frequency" word="current" count="6"/>
 <result title="frequency" word="double;" count="6"/>
 <result title="frequency" word="functions" count="6"/>
 <result title="frequency" word="generally" count="6"/>
 <result title="frequency" word="highest" count="6"/>
 <result title="frequency" word="increase" count="6"/>
 <result title="frequency" word="information" count="6"/>
 <result title="frequency" word="key" count="6"/>
 <result title="frequency" word="lack" count="6"/>
 <result title="frequency" word="leading" count="6"/>
 <result title="frequency" word="limited" count="6"/>
 <result title="frequency" word="needed" count="6"/>
 <result title="frequency" word="new" count="6"/>
 <result title="frequency" word="outcomes" count="6"/>
 <result title="frequency" word="poor" count="6"/>
 <result title="frequency" word="primary" count="6"/>
 <result title="frequency" word="road" count="6"/>
 <result title="frequency" word="use" count="6"/>
 <result title="frequency" word="world." count="6"/>
 <result title="frequency" word="Bank," count="5"/>
 <result title="frequency" word="HIV/AIDS" count="5"/>
 <result title="frequency" word="Jordan," count="5"/>
 <result title="frequency" word="Kuwait," count="5"/>
 <result title="frequency" word="Mediterranean" count="5"/>
 <result title="frequency" word="Morocco," count="5"/>
 <result title="frequency" word="Oman" count="5"/>
 <result title="frequency" word="Policy" count="5"/>
 <result title="frequency" word="Table" count="5"/>
 <result title="frequency" word="access" count="5"/>
 <result title="frequency" word="age" count="5"/>
 <result title="frequency" word="benefit" count="5"/>
 <result title="frequency" word="better" count="5"/>
 <result title="frequency" word="biomedical" count="5"/>
 <result title="frequency" word="births" count="5"/>
 <result title="frequency" word="border-color" count="5"/>
 <result title="frequency" word="border-width" count="5"/>
 <result title="frequency" word="capita" count="5"/>
 <result title="frequency" word="challenges," count="5"/>
 <result title="frequency" word="countries." count="5"/>
 <result title="frequency" word="death" count="5"/>
 <result title="frequency" word="demographic" count="5"/>
 <result title="frequency" word="disparities" count="5"/>
 <result title="frequency" word="effective" count="5"/>
 <result title="frequency" word="expenditure" count="5"/>
 <result title="frequency" word="facing" count="5"/>
 <result title="frequency" word="female" count="5"/>
 <result title="frequency" word="financial" count="5"/>
 <result title="frequency" word="foreign" count="5"/>
 <result title="frequency" word="growing" count="5"/>
 <result title="frequency" word="health-care" count="5"/>
 <result title="frequency" word="health-related" count="5"/>
 <result title="frequency" word="increasingly" count="5"/>
 <result title="frequency" word="issues" count="5"/>
 <result title="frequency" word="leadership" count="5"/>
 <result title="frequency" word="like" count="5"/>
 <result title="frequency" word="low" count="5"/>
 <result title="frequency" word="make" count="5"/>
 <result title="frequency" word="numbers" count="5"/>
 <result title="frequency" word="people" count="5"/>
 <result title="frequency" word="physical" count="5"/>
 <result title="frequency" word="population," count="5"/>
 <result title="frequency" word="populations" count="5"/>
 <result title="frequency" word="protection" count="5"/>
 <result title="frequency" word="provide" count="5"/>
 <result title="frequency" word="providing" count="5"/>
 <result title="frequency" word="rising" count="5"/>
 <result title="frequency" word="rural" count="5"/>
 <result title="frequency" word="solid;" count="5"/>
 <result title="frequency" word="surveillance" count="5"/>
 <result title="frequency" word="systems." count="5"/>
 <result title="frequency" word="total" count="5"/>
 <result title="frequency" word="traffic" count="5"/>
 <result title="frequency" word="transitions" count="5"/>
 <result title="frequency" word="weak" count="5"/>
 <result title="frequency" word="{font-style" count="5"/>
 <result title="frequency" word="{font-weight" count="5"/>
 <result title="frequency" word="(Both" count="4"/>
 <result title="frequency" word=".To" count="4"/>
 <result title="frequency" word="According" count="4"/>
 <result title="frequency" word="Africa:" count="4"/>
 <result title="frequency" word="Algeria" count="4"/>
 <result title="frequency" word="Arabia" count="4"/>
 <result title="frequency" word="Arabia," count="4"/>
 <result title="frequency" word="COVID-" count="4"/>
 <result title="frequency" word="Country" count="4"/>
 <result title="frequency" word="DC," count="4"/>
 <result title="frequency" word="Eastern" count="4"/>
 <result title="frequency" word="Egypt," count="4"/>
 <result title="frequency" word="However," count="4"/>
 <result title="frequency" word="Iran" count="4"/>
 <result title="frequency" word="Iraq," count="4"/>
 <result title="frequency" word="Kuwait" count="4"/>
 <result title="frequency" word="Lebanon," count="4"/>
 <result title="frequency" word="NCDs," count="4"/>
 <result title="frequency" word="Oman," count="4"/>
 <result title="frequency" word="Qatar," count="4"/>
 <result title="frequency" word="References" count="4"/>
 <result title="frequency" word="Report" count="4"/>
 <result title="frequency" word="Reproduced" count="4"/>
 <result title="frequency" word="Republic" count="4"/>
 <result title="frequency" word="Strategy" count="4"/>
 <result title="frequency" word="Syria," count="4"/>
 <result title="frequency" word="Traditional" count="4"/>
 <result title="frequency" word="West" count="4"/>
 <result title="frequency" word="Yemen," count="4"/>
 <result title="frequency" word="achieve" count="4"/>
 <result title="frequency" word="availability" count="4"/>
 <result title="frequency" word="beds" count="4"/>
 <result title="frequency" word="bold" count="4"/>
 <result title="frequency" word="care." count="4"/>
 <result title="frequency" word="centre" count="4"/>
 <result title="frequency" word="characterized" count="4"/>
 <result title="frequency" word="communicable" count="4"/>
 <result title="frequency" word="comprehensive" count="4"/>
 <result title="frequency" word="courier;" count="4"/>
 <result title="frequency" word="despite" count="4"/>
 <result title="frequency" word="different" count="4"/>
 <result title="frequency" word="drug" count="4"/>
 <result title="frequency" word="economic" count="4"/>
 <result title="frequency" word="em;" count="4"/>
 <result title="frequency" word="emerging" count="4"/>
 <result title="frequency" word="estimates" count="4"/>
 <result title="frequency" word="existing" count="4"/>
 <result title="frequency" word="financing" count="4"/>
 <result title="frequency" word="governance" count="4"/>
 <result title="frequency" word="hospital" count="4"/>
 <result title="frequency" word="households" count="4"/>
 <result title="frequency" word="increases" count="4"/>
 <result title="frequency" word="infant" count="4"/>
 <result title="frequency" word="insurance" count="4"/>
 <result title="frequency" word="low-income" count="4"/>
 <result title="frequency" word="measures" count="4"/>
 <result title="frequency" word="middle-income" count="4"/>
 <result title="frequency" word="ongoing" count="4"/>
 <result title="frequency" word="organization" count="4"/>
 <result title="frequency" word="political" count="4"/>
 <result title="frequency" word="populations." count="4"/>
 <result title="frequency" word="practitioners" count="4"/>
 <result title="frequency" word="provision" count="4"/>
 <result title="frequency" word="pt;}" count="4"/>
 <result title="frequency" word="recent" count="4"/>
 <result title="frequency" word="resources," count="4"/>
 <result title="frequency" word="role" count="4"/>
 <result title="frequency" word="sexes)" count="4"/>
 <result title="frequency" word="staff" count="4"/>
 <result title="frequency" word="terms" count="4"/>
 <result title="frequency" word="track" count="4"/>
 <result title="frequency" word="transition" count="4"/>
 <result title="frequency" word="universal" count="4"/>
 <result title="frequency" word="used" count="4"/>
 <result title="frequency" word="world" count="4"/>
</results>
