<?xml version="1.0" encoding="UTF-8"?>
<results title="frequencies">
 <result title="frequency" word="cell" count="127"/>
 <result title="frequency" word="\documentclass[pt]{minimal}" count="125"/>
 <result title="frequency" word="\setlength{\oddsidemargin}{-pt}" count="125"/>
 <result title="frequency" word="\usepackage{amsbsy}" count="125"/>
 <result title="frequency" word="\usepackage{amsfonts}" count="125"/>
 <result title="frequency" word="\usepackage{amsmath}" count="125"/>
 <result title="frequency" word="\usepackage{amssymb}" count="125"/>
 <result title="frequency" word="\usepackage{mathrsfs}" count="125"/>
 <result title="frequency" word="\usepackage{upgreek}" count="125"/>
 <result title="frequency" word="\usepackage{wasysym}" count="125"/>
 <result title="frequency" word="cells" count="71"/>
 <result title="frequency" word="polarisation" count="38"/>
 <result title="frequency" word="model" count="36"/>
 <result title="frequency" word="contractility" count="32"/>
 <result title="frequency" word="migration" count="32"/>
 <result title="frequency" word="\begin{document}$${\lambda" count="30"/>
 <result title="frequency" word="collective" count="27"/>
 <result title="frequency" word="polarity" count="27"/>
 <result title="frequency" word="wave" count="27"/>
 <result title="frequency" word="Fig." count="25"/>
 <result title="frequency" word="leading" count="24"/>
 <result title="frequency" word="$$\end{document}" count="22"/>
 <result title="frequency" word="cortex" count="22"/>
 <result title="frequency" word="motile" count="22"/>
 <result title="frequency" word="{border-style" count="20"/>
 <result title="frequency" word="Cell" count="18"/>
 <result title="frequency" word="cont" count="18"/>
 <result title="frequency" word="edge" count="18"/>
 <result title="frequency" word="force" count="18"/>
 <result title="frequency" word="motility" count="18"/>
 <result title="frequency" word="px;}" count="18"/>
 <result title="frequency" word="swirling" count="18"/>
 <result title="frequency" word="#ffffff;}" count="17"/>
 <result title="frequency" word="area" count="17"/>
 <result title="frequency" word="velocity" count="17"/>
 <result title="frequency" word="barrier" count="16"/>
 <result title="frequency" word="adhesion" count="15"/>
 <result title="frequency" word="dynamics" count="15"/>
 <result title="frequency" word="max" count="15"/>
 <result title="frequency" word="parameter" count="15"/>
 <result title="frequency" word="\begin{document}$${F}_{{\rm{\max" count="14"/>
 <result title="frequency" word="propagation" count="14"/>
 <result title="frequency" word="epithelial" count="12"/>
 <result title="frequency" word="simulation" count="12"/>
 <result title="frequency" word="}$$\end{document}" count="12"/>
 <result title="frequency" word="Table" count="11"/>
 <result title="frequency" word="\begin{document}$$x$$\end{document}" count="11"/>
 <result title="frequency" word="cell-cell" count="11"/>
 <result title="frequency" word="monolayer" count="11"/>
 <result title="frequency" word="single" count="11"/>
 <result title="frequency" word="&amp;gt;" count="10"/>
 <result title="frequency" word="cellular" count="10"/>
 <result title="frequency" word="lattice" count="10"/>
 <result title="frequency" word="}_{{\rm{cont}}}$$\end{document}" count="10"/>
 <result title="frequency" word="Figure" count="9"/>
 <result title="frequency" word="adh" count="9"/>
 <result title="frequency" word="cells." count="9"/>
 <result title="frequency" word="center" count="9"/>
 <result title="frequency" word="cortical" count="9"/>
 <result title="frequency" word="displacement" count="9"/>
 <result title="frequency" word="energy" count="9"/>
 <result title="frequency" word="parameters" count="9"/>
 <result title="frequency" word="set" count="9"/>
 <result title="frequency" word="sheet" count="9"/>
 <result title="frequency" word="speed" count="9"/>
 <result title="frequency" word="Supplementary" count="8"/>
 <result title="frequency" word="active" count="8"/>
 <result title="frequency" word="cell-free" count="8"/>
 <result title="frequency" word="initial" count="8"/>
 <result title="frequency" word="intracellular" count="8"/>
 <result title="frequency" word="mechanical" count="8"/>
 <result title="frequency" word="migrating" count="8"/>
 <result title="frequency" word="motion" count="8"/>
 <result title="frequency" word="order" count="8"/>
 <result title="frequency" word="pixel" count="8"/>
 <result title="frequency" word="px;" count="8"/>
 <result title="frequency" word="region" count="8"/>
 <result title="frequency" word="simulations" count="8"/>
 <result title="frequency" word="value" count="8"/>
 <result title="frequency" word="{font-family" count="8"/>
 <result title="frequency" word="}}}$$\end{document}" count="8"/>
 <result title="frequency" word="(a)." count="7"/>
 <result title="frequency" word="Review" count="7"/>
 <result title="frequency" word="Thus," count="7"/>
 <result title="frequency" word="\begin{document}$$\alpha" count="7"/>
 <result title="frequency" word="average" count="7"/>
 <result title="frequency" word="corresponding" count="7"/>
 <result title="frequency" word="font-size" count="7"/>
 <result title="frequency" word="magnitude" count="7"/>
 <result title="frequency" word="models" count="7"/>
 <result title="frequency" word="onset" count="7"/>
 <result title="frequency" word="represents" count="7"/>
 <result title="frequency" word="shapes" count="7"/>
 <result title="frequency" word="tissue" count="7"/>
 <result title="frequency" word="trajectories" count="7"/>
 <result title="frequency" word="using" count="7"/>
 <result title="frequency" word="wound" count="7"/>
 <result title="frequency" word="(a)" count="6"/>
 <result title="frequency" word="(b)" count="6"/>
 <result title="frequency" word="(e.g.," count="6"/>
 <result title="frequency" word="CPM" count="6"/>
 <result title="frequency" word="Computational" count="6"/>
 <result title="frequency" word="Information." count="6"/>
 <result title="frequency" word="LINK" count="6"/>
 <result title="frequency" word="Model" count="6"/>
 <result title="frequency" word="Potts" count="6"/>
 <result title="frequency" word="\begin{document}$${\overrightarrow{F}}_{\sigma" count="6"/>
 <result title="frequency" word="alignment" count="6"/>
 <result title="frequency" word="cells," count="6"/>
 <result title="frequency" word="change" count="6"/>
 <result title="frequency" word="coefficient" count="6"/>
 <result title="frequency" word="double;" count="6"/>
 <result title="frequency" word="end" count="6"/>
 <result title="frequency" word="free" count="6"/>
 <result title="frequency" word="interactions" count="6"/>
 <result title="frequency" word="intercellular" count="6"/>
 <result title="frequency" word="position" count="6"/>
 <result title="frequency" word="shown" count="6"/>
 <result title="frequency" word="sites" count="6"/>
 <result title="frequency" word="term" count="6"/>
 <result title="frequency" word="time" count="6"/>
 <result title="frequency" word="}_{{\rm{adh}}}$$\end{document}" count="6"/>
 <result title="frequency" word="(Fig." count="5"/>
 <result title="frequency" word="Biologye./journal.pcbi." count="5"/>
 <result title="frequency" word="bin" count="5"/>
 <result title="frequency" word="border-color" count="5"/>
 <result title="frequency" word="border-width" count="5"/>
 <result title="frequency" word="constant" count="5"/>
 <result title="frequency" word="coupled" count="5"/>
 <result title="frequency" word="directed" count="5"/>
 <result title="frequency" word="earlier" count="5"/>
 <result title="frequency" word="function" count="5"/>
 <result title="frequency" word="mass" count="5"/>
 <result title="frequency" word="migration." count="5"/>
 <result title="frequency" word="monolayer." count="5"/>
 <result title="frequency" word="movements" count="5"/>
 <result title="frequency" word="number" count="5"/>
 <result title="frequency" word="regime" count="5"/>
 <result title="frequency" word="results" count="5"/>
 <result title="frequency" word="solid;" count="5"/>
 <result title="frequency" word="spontaneous" count="5"/>
 <result title="frequency" word="stage" count="5"/>
 <result title="frequency" word="values" count="5"/>
 <result title="frequency" word="various" count="5"/>
 <result title="frequency" word="weak" count="5"/>
 <result title="frequency" word="{font-style" count="5"/>
 <result title="frequency" word="{font-weight" count="5"/>
 <result title="frequency" word="(a,b)." count="4"/>
 <result title="frequency" word="(b)," count="4"/>
 <result title="frequency" word="Academy" count="4"/>
 <result title="frequency" word="Collective" count="4"/>
 <result title="frequency" word="Commons" count="4"/>
 <result title="frequency" word="Creative" count="4"/>
 <result title="frequency" word="E./PhysRevE.." count="4"/>
 <result title="frequency" word="Epithelial" count="4"/>
 <result title="frequency" word="Eqs." count="4"/>
 <result title="frequency" word="However," count="4"/>
 <result title="frequency" word="Journal./j.bpj..." count="4"/>
 <result title="frequency" word="Molecular" count="4"/>
 <result title="frequency" word="Movie" count="4"/>
 <result title="frequency" word="National" count="4"/>
 <result title="frequency" word="Sciences./pnas." count="4"/>
 <result title="frequency" word="\begin{document}$$\Phi" count="4"/>
 <result title="frequency" word="\begin{document}$$\overrightarrow{j}$$\end{document}" count="4"/>
 <result title="frequency" word="al.Collective" count="4"/>
 <result title="frequency" word="biological" count="4"/>
 <result title="frequency" word="bistable" count="4"/>
 <result title="frequency" word="bold" count="4"/>
 <result title="frequency" word="bulk" count="4"/>
 <result title="frequency" word="calculate" count="4"/>
 <result title="frequency" word="changes" count="4"/>
 <result title="frequency" word="closure" count="4"/>
 <result title="frequency" word="compressibility" count="4"/>
 <result title="frequency" word="contractile" count="4"/>
 <result title="frequency" word="courier;" count="4"/>
 <result title="frequency" word="determined" count="4"/>
 <result title="frequency" word="development" count="4"/>
 <result title="frequency" word="different" count="4"/>
 <result title="frequency" word="domain." count="4"/>
 <result title="frequency" word="elementary" count="4"/>
 <result title="frequency" word="em;" count="4"/>
 <result title="frequency" word="equilibrium" count="4"/>
 <result title="frequency" word="expansion" count="4"/>
 <result title="frequency" word="experimental" count="4"/>
 <result title="frequency" word="gradually" count="4"/>
 <result title="frequency" word="i.e." count="4"/>
 <result title="frequency" word="i.e.," count="4"/>
 <result title="frequency" word="increase" count="4"/>
 <result title="frequency" word="indicate" count="4"/>
 <result title="frequency" word="lifted," count="4"/>
 <result title="frequency" word="likely" count="4"/>
 <result title="frequency" word="line" count="4"/>
 <result title="frequency" word="migrate" count="4"/>
 <result title="frequency" word="migration," count="4"/>
 <result title="frequency" word="observed" count="4"/>
 <result title="frequency" word="one-dimensional" count="4"/>
 <result title="frequency" word="overall" count="4"/>
 <result title="frequency" word="pixels" count="4"/>
 <result title="frequency" word="presence" count="4"/>
 <result title="frequency" word="process" count="4"/>
 <result title="frequency" word="properties" count="4"/>
 <result title="frequency" word="pt;}" count="4"/>
 <result title="frequency" word="stationary" count="4"/>
 <result title="frequency" word="steady-state" count="4"/>
 <result title="frequency" word="step" count="4"/>
 <result title="frequency" word="stochastic" count="4"/>
 <result title="frequency" word="tension" count="4"/>
 <result title="frequency" word="threshold" count="4"/>
 <result title="frequency" word="use" count="4"/>
 <result title="frequency" word="versus" count="4"/>
 <result title="frequency" word="wave," count="4"/>
 <result title="frequency" word=" × " count="4"/>
</results>
